Django_Lookout-0.1.2.dist-info/DESCRIPTION.rst
Django_Lookout-0.1.2.dist-info/LICENSE.txt
Django_Lookout-0.1.2.dist-info/METADATA
Django_Lookout-0.1.2.dist-info/RECORD
Django_Lookout-0.1.2.dist-info/WHEEL
Django_Lookout-0.1.2.dist-info/metadata.json
Django_Lookout-0.1.2.dist-info/top_level.txt
lookout/VERSION.txt
lookout/__init__.py
lookout/admin.py
lookout/apps.py
lookout/exceptions.py
lookout/logging.py
lookout/models.py
lookout/tests.py
lookout/urls.py
lookout/utils.py
lookout/views.py
lookout/docs/logo.svg
lookout/migrations/0001_initial.py
lookout/migrations/0002_auto_20171008_2238.py
lookout/migrations/0002_v0_1_2.py
lookout/migrations/0003_auto_20171008_2324.py
lookout/migrations/0004_v0_1_1.py
lookout/migrations/__init__.py
lookout/report_schemas/__init__.py
lookout/report_schemas/base.py
lookout/report_schemas/csp.py
lookout/report_schemas/fallback.py
lookout/report_schemas/generic.py
lookout/report_schemas/hpkp.py
lookout/report_schemas/legacy.py
lookout/templates/admin/lookout/change_form.html
