Metadata-Version: 2.0
Name: Django-Lookout
Version: 0.1.2
Summary: API endpoint for receiving incident reports from Content Security Policy (CSP), HTTP Public Key Pinning (HPKP), and the HTTP Reporting API.
Home-page: https://github.com/rspeed/Django-Lookout
Author: Rob Speed
Author-email: rspeed@bounteo.us
License: MIT
Keywords: django csp hpkp security error-monitoring https
Platform: UNKNOWN
Classifier: Development Status :: 2 - Pre-Alpha
Classifier: Environment :: Web Environment
Classifier: Framework :: Django :: 1.10
Classifier: Intended Audience :: Developers
Classifier: Intended Audience :: Information Technology
Classifier: License :: OSI Approved :: MIT License
Classifier: Natural Language :: English
Classifier: Programming Language :: Python :: 3.5
Classifier: Programming Language :: Python :: 3.6
Classifier: Topic :: Internet :: WWW/HTTP :: Site Management
Classifier: Topic :: Security
Classifier: Topic :: Security :: Cryptography
Classifier: Topic :: System :: Logging
Classifier: Topic :: System :: Monitoring
Requires-Python: >=3.5
Requires-Dist: Django
Requires-Dist: Pygments
Requires-Dist: jsonschema
Requires-Dist: pytz
